lean/__init__.py
lean/click.py
lean/constants.py
lean/container.py
lean/main.py
lean/commands/__init__.py
lean/commands/backtest.py
lean/commands/build.py
lean/commands/create_project.py
lean/commands/delete_project.py
lean/commands/init.py
lean/commands/lean.py
lean/commands/login.py
lean/commands/logout.py
lean/commands/logs.py
lean/commands/optimize.py
lean/commands/report.py
lean/commands/research.py
lean/commands/whoami.py
lean/commands/cloud/__init__.py
lean/commands/cloud/backtest.py
lean/commands/cloud/optimize.py
lean/commands/cloud/pull.py
lean/commands/cloud/push.py
lean/commands/cloud/status.py
lean/commands/cloud/live/__init__.py
lean/commands/cloud/live/deploy.py
lean/commands/cloud/live/liquidate.py
lean/commands/cloud/live/live.py
lean/commands/cloud/live/stop.py
lean/commands/config/__init__.py
lean/commands/config/get.py
lean/commands/config/list.py
lean/commands/config/set.py
lean/commands/config/unset.py
lean/commands/data/__init__.py
lean/commands/data/download.py
lean/commands/data/generate.py
lean/commands/gui/__init__.py
lean/commands/library/__init__.py
lean/commands/library/add.py
lean/commands/library/remove.py
lean/commands/live/__init__.py
lean/commands/live/add_security.py
lean/commands/live/cancel_order.py
lean/commands/live/deploy.py
lean/commands/live/liquidate.py
lean/commands/live/live.py
lean/commands/live/stop.py
lean/commands/live/submit_order.py
lean/commands/live/update_order.py
lean/components/__init__.py
lean/components/api/__init__.py
lean/components/api/account_client.py
lean/components/api/api_client.py
lean/components/api/backtest_client.py
lean/components/api/compile_client.py
lean/components/api/data_client.py
lean/components/api/file_client.py
lean/components/api/lean_client.py
lean/components/api/live_client.py
lean/components/api/market_client.py
lean/components/api/module_client.py
lean/components/api/node_client.py
lean/components/api/optimization_client.py
lean/components/api/organization_client.py
lean-1.155.dist-info/LICENSE
lean-1.155.dist-info/METADATA
lean-1.155.dist-info/WHEEL
lean-1.155.dist-info/entry_points.txt
lean-1.155.dist-info/top_level.txt
lean-1.155.dist-info/RECORD
