Metadata-Version: 2.1
Name: lean
Version: 1.155
Summary: A CLI aimed at making it easier to run QuantConnect's LEAN engine locally and in the cloud
Home-page: https://lean.io/cli
Author: QuantConnect
Author-email: support@quantconnect.com
License: UNKNOWN
Project-URL: Documentation, https://www.lean.io/docs/v2/lean-cli/key-concepts/getting-started
Project-URL: Source, https://github.com/QuantConnect/lean-cli
Platform: UNKNOWN
Classifier: Development Status :: 5 - Production/Stable
Classifier: Intended Audience :: Developers
Classifier: Intended Audience :: Financial and Insurance Industry
Classifier: License :: OSI Approved :: Apache Software License
Classifier: Programming Language :: Python :: 3
Classifier: Programming Language :: Python :: 3.7
Classifier: Programming Language :: Python :: 3.8
Classifier: Programming Language :: Python :: 3.9
Classifier: Programming Language :: Python :: 3.10
Requires-Python: >= 3.7
Requires-Dist: click (>=8.0.4)
Requires-Dist: requests (>=2.27.1)
Requires-Dist: json5 (>=0.9.8)
Requires-Dist: docker (>=6.0.0)
Requires-Dist: rich (>=9.10.0)
Requires-Dist: pydantic (>=1.8.2)
Requires-Dist: python-dateutil (>=2.8.2)
Requires-Dist: lxml (>=4.9.0)
Requires-Dist: maskpass (>=0.3.6)
Requires-Dist: joblib (>=1.1.0)
Requires-Dist: wrapt (~=1.14.1)
Requires-Dist: setuptools
Requires-Dist: quantconnect-stubs (>=15527)
